{
  "run_timestamp": "2026-04-19",
  "window": {"start": "2025-08-01", "end": "2025-10-31"},
  "decision": "proceed",
  "abort_threshold": 30,
  "thin_threshold": 15,
  "volumes": {
    "general": {
      "mbg_umum_phrase":  {"count": 263,  "mode": "fast", "status": "ok"},
      "mbg_umum_short":   {"count": 4996, "mode": "csv",  "status": "ok"},
      "mbg_umum_context": {"count": 5194, "mode": "csv",  "status": "ok"}
    },
    "tray": {
      "tray_umum_objek":   {"count": 227, "mode": "fast", "status": "ok"},
      "tray_suhu_basi":    {"count": 14,  "mode": "fast", "status": "thin"},
      "tray_tumpah_tutup": {"count": 8,   "mode": "fast", "status": "thin"},
      "tray_material":     {"count": 82,  "mode": "fast", "status": "ok"},
      "tray_distribusi":   {"count": 7,   "mode": "fast", "status": "thin"},
      "tray_higienitas":   {"count": 47,  "mode": "fast", "status": "ok"}
    }
  },
  "totals": {
    "general_gross": 10453,
    "tray_gross": 385,
    "tray_unique_estimate": 230
  },
  "skipped_packs": []
}
